{
  "currentPlayer": 0,
  "diceResult": {
    "canTakeOff": true,
    "lucky": false,
    "raw": [
      6,
      2,
      2
    ],
    "result": [
      1,
      2,
      3,
      4,
      5,
      6,
      7,
      8,
      9,
      10,
      11,
      12,
      13,
      14,
      15,
      16,
      17,
      18
    ]
  },
  "luckyCount": 0,
  "movedPiecesUUID": [],
  "name": "Game1",
  "pieces": [
    {
      "cellType": "Normal",
      "color": "Red",
      "index": 8,
      "uuid": "e9871417-eb6e-4602-b00f-ac8806bd722e"
    },
    {
      "cellType": "Takeoff",
      "color": "Red",
      "index": 0,
      "uuid": "c034d3ae-42f7-42d4-958a-36c1fccb6e7f"
    },
    {
      "cellType": "ParkingApron",
      "color": "Red",
      "index": 2,
      "uuid": "67d185d8-26fe-45f0-b5c3-725c240b161e"
    },
    {
      "cellType": "Takeoff",
      "color": "Red",
      "index": 0,
      "uuid": "dc7807b9-8c8c-4b47-a32d-886b07baa9ca"
    },
    {
      "cellType": "Normal",
      "color": "Yellow",
      "index": 9,
      "uuid": "8a10fcff-0229-49b3-aafc-5a628d250bb5"
    },
    {
      "cellType": "ParkingApron",
      "color": "Yellow",
      "index": 1,
      "uuid": "7e5ae26f-2759-4346-8c98-d9a73b0b32db"
    },
    {
      "cellType": "ParkingApron",
      "color": "Yellow",
      "index": 2,
      "uuid": "d397d3c2-535e-453d-a380-979fff686ced"
    },
    {
      "cellType": "Normal",
      "color": "Yellow",
      "index": 9,
      "uuid": "14e4b4f2-cf25-4f73-b2b4-800dbe354cd2"
    },
    {
      "cellType": "ParkingApron",
      "color": "Blue",
      "index": 0,
      "uuid": "8bf30fc1-a0cc-4917-b536-2dfdea0ea3a5"
    },
    {
      "cellType": "ParkingApron",
      "color": "Blue",
      "index": 1,
      "uuid": "de542a0f-e96b-4ce4-888f-f045dcbe8595"
    },
    {
      "cellType": "ParkingApron",
      "color": "Blue",
      "index": 2,
      "uuid": "44b2e58b-2f6f-4718-9d02-759865e01f78"
    },
    {
      "cellType": "ParkingApron",
      "color": "Blue",
      "index": 3,
      "uuid": "0633faa2-81d1-4f32-841f-dfd2a5fb2220"
    },
    {
      "cellType": "ParkingApron",
      "color": "Green",
      "index": 0,
      "uuid": "4222b798-5222-40a9-8eb4-a68d12e24b1e"
    },
    {
      "cellType": "ParkingApron",
      "color": "Green",
      "index": 1,
      "uuid": "ba1cbc7f-f47c-41c2-97ca-42cf193b726b"
    },
    {
      "cellType": "ParkingApron",
      "color": "Green",
      "index": 2,
      "uuid": "0e2ee3d5-17d0-4567-b0a8-3c519f63ae52"
    },
    {
      "cellType": "ParkingApron",
      "color": "Green",
      "index": 3,
      "uuid": "afe44753-6892-4389-9e79-7464ffbb2c83"
    }
  ],
  "settings": {
    "battle": true,
    "diceNumber": 3,
    "playerNumber": 2,
    "stack": true
  },
  "walkable": false
}